setup.cfg
setup.py
gutter/appengine/__init__.py
gutter/appengine/forms.py
gutter/appengine/handlers.py
gutter/appengine/main.py
gutter/appengine/manager.py
gutter/appengine/models.py
gutter/appengine/registry.py
gutter/appengine/wtforms_extension.py
gutter/appengine/static/img/lonely.gif
gutter/appengine/static/js/gutter.js
gutter/appengine/templates/_switch.html
gutter/appengine/templates/index.html
gutter_appengine.egg-info/PKG-INFO
gutter_appengine.egg-info/SOURCES.txt
gutter_appengine.egg-info/dependency_links.txt
gutter_appengine.egg-info/namespace_packages.txt
gutter_appengine.egg-info/requires.txt
gutter_appengine.egg-info/top_level.txt