Metadata-Version: 1.1
Name: gutter-appengine
Version: 1.0.1
Summary: An AppEngine front-end to gutter.
Home-page: https://github.com/soofaloofa/gutter-appengine
Author: Kevin Sookocheff
Author-email: kevin.sookocheff@gmail.com
License: MIT
Platform: UNKNOWN
Classifier: Development Status :: 5 - Production/Stable
Classifier: Intended Audience :: Developers
Classifier: Natural Language :: English
Classifier: License :: OSI Approved :: MIT License
Classifier: Operating System :: OS Independent
Classifier: Programming Language :: Python
Classifier: Programming Language :: Python :: 2
Classifier: Programming Language :: Python :: 2.6
Classifier: Programming Language :: Python :: 2.7
Classifier: Topic :: Software Development :: Libraries :: Python Modules
